<?xml version="1.0" encoding="utf-8"?>
<DacOrigin xmlns="http://schemas.microsoft.com/sqlserver/dac/Serialization/2012/02">
  <PackageProperties>
    <Version>3.0.0.0</Version>
    <ContainsExportedData>true</ContainsExportedData>
    <StreamVersions>
      <Version StreamName="Data">2.0.0.0</Version>
      <Version StreamName="DeploymentContributors">1.0.0.0</Version>
    </StreamVersions>
  </PackageProperties>
  <Operation>
    <Identity>bff9b851-8645-4253-84b4-59b047311308</Identity>
    <Start>2021-10-17T22:25:52.6203927-06:00</Start>
    <End>0001-01-01T00:00:00.0000000</End>
    <ProductName>Microsoft.SqlServer.Dac, Version=15.0.0.0, Culture=neutral, PublicKeyToken=b03f5f7f11d50a3a</ProductName>
    <ProductVersion>15.0.5282.3</ProductVersion>
    <ProductSchema>http://schemas.microsoft.com/sqlserver/dac/Serialization/2012/02</ProductSchema>
  </Operation>
  <Server>
    <ServerVersion>Microsoft SQL Server 2019 (RTM) - 15.0.2000.5 (X64) 
	Sep 24 2019 13:48:23 
	Copyright (C) 2019 Microsoft Corporation
	Express Edition (64-bit) on Windows 10 Pro 10.0 &lt;X64&gt; (Build 19042: )
</ServerVersion>
    <ObjectCounts>
      <DatabaseOptions>1</DatabaseOptions>
      <PermissionStatement>2</PermissionStatement>
      <PrimaryKeyConstraint>1</PrimaryKeyConstraint>
      <SimpleColumn>4</SimpleColumn>
      <Table>1</Table>
    </ObjectCounts>
  </Server>
  <ExportStatistics>
    <SourceDatabaseSize>10928</SourceDatabaseSize>
    <TableRowCountTotalTag>0</TableRowCountTotalTag>
  </ExportStatistics>
  <Checksums>
    <Checksum Uri="/model.xml">064F3121B4A4E17BD9CD406EFCCB0F43856D5A2A233A29DD05195896120FD118</Checksum>
  </Checksums>
  <ModelSchemaVersion>2.9</ModelSchemaVersion>
</DacOrigin>